{"ids": [], "num_scenes": [8, 9, 13], "num_actors": [10, 11, 15], "obj": [13, 41, 691], "init_time": [0.015, 0.022, 0.053], "solve_time": [0.203, 0.604, 9.236], "num_vars": [533, 662, 1292], "sln_status": ["OPTIMAL_SOLUTION", "OPTIMAL_SOLUTION", "SATISFIED"], "instance_name": ["input_10_8_5_4.json", "input_11_9_6_5.json", "input_15_13_10_9.json"], "scene_order": [[2, 1, 8, 4, 3, 5, 7, 6], [3, 6, 1, 5, 7, 4, 2, 9, 8], [12, 11, 10, 1, 3, 6, 2, 5, 9, 7, 8, 4, 13]], "mdl_name": ["talent_model1.mzn", "talent_model1.mzn", "talent_model1.mzn"]}